employee_analytics_mcp-0.1.5.dist-info/licenses/LICENSE
server/__init__.py
server/employee_analytics.py
server/employee_analytics_core.py
employee_analytics_mcp-0.1.5.dist-info/METADATA
employee_analytics_mcp-0.1.5.dist-info/WHEEL
employee_analytics_mcp-0.1.5.dist-info/top_level.txt
employee_analytics_mcp-0.1.5.dist-info/RECORD
