Metadata-Version: 2.4
Name: employee-analytics-mcp
Version: 0.1.5
Summary: An MCP server for employee analytics
Author-email: Nancy Madan <nanacymadan.6@gmail.com>
Requires-Python: >=3.8
License-File: LICENSE
Requires-Dist: psycopg2
Requires-Dist: httpx
Requires-Dist: python-dotenv
Dynamic: license-file
